clowdr/__init__.py
clowdr/driver.py
clowdr/server.py
clowdr/task.py
clowdr/utils.py
clowdr/controller/__init__.py
clowdr/controller/launcher.py
clowdr/controller/metadata.py
clowdr/controller/rerunner.py
clowdr/endpoint/AWS.py
clowdr/endpoint/__init__.py
clowdr/endpoint/remote.py
clowdr/share/__init__.py
clowdr/share/consolidate.py
clowdr/share/customDash.py
clowdr/share/portal.py
clowdr/templates/index.html
clowdr/templates/AWS/computeEnvironment.json
clowdr/templates/AWS/jobDefinition.json
clowdr/templates/AWS/jobQueue.json
clowdr/templates/AWS/userRoles.json
clowdr-0.1.2.post1.dist-info/LICENSE
clowdr-0.1.2.post1.dist-info/METADATA
clowdr-0.1.2.post1.dist-info/WHEEL
clowdr-0.1.2.post1.dist-info/entry_points.txt
clowdr-0.1.2.post1.dist-info/top_level.txt
clowdr-0.1.2.post1.dist-info/RECORD
