Metadata-Version: 2.1
Name: clowdr
Version: 0.1.2.post1
Summary: Tool for launching pipelines locally and remotely
Home-page: http://github.com/clowdr/clowdr
Author: Gregory Kiar
Author-email: gkiar07@gmail.com
License: MIT
Platform: UNKNOWN
Classifier: Programming Language :: Python
Classifier: Programming Language :: Python :: 3
Classifier: Programming Language :: Python :: 3.5
Classifier: Programming Language :: Python :: 3.6
Classifier: Programming Language :: Python :: 3.7
Classifier: Programming Language :: Python :: Implementation :: PyPy
Classifier: License :: OSI Approved :: MIT License
Classifier: Topic :: Software Development :: Libraries :: Python Modules
Classifier: Operating System :: OS Independent
Classifier: Natural Language :: English
Requires-Python: >=3
Requires-Dist: boto3
Requires-Dist: flask
Requires-Dist: boutiques (>=0.5.10)
Requires-Dist: pandas (>=0.23)
Requires-Dist: slurmpy (==0.0.7)
Requires-Dist: dash (>=0.24.1)
Requires-Dist: dash-renderer (>=0.13.0)
Requires-Dist: dash-html-components (>=0.11.0)
Requires-Dist: dash-core-components (>=0.27.1)
Requires-Dist: dash-table-experiments (>=0.6.0)
Requires-Dist: colorlover
Requires-Dist: psutil
Requires-Dist: plotly (>=3.1.1)
